walnut_agent/__about__.py
walnut_agent/__init__.py
walnut_agent/ios_monkey.py
walnut_agent/common/Fzpagpoco.py
walnut_agent/common/Fzpoco.py
walnut_agent/common/HTMLTestRunner_PY3.py
walnut_agent/common/Install_yuerpage.py
walnut_agent/common/__init__.py
walnut_agent/common/basic.py
walnut_agent/common/config.py
walnut_agent/common/do_db.py
walnut_agent/common/do_json.py
walnut_agent/common/do_monkeylog.py
walnut_agent/common/http_request.py
walnut_agent/common/mail.py
walnut_agent/common/make_file.py
walnut_agent/common/old.py
walnut_agent/common/runtest_email.py
walnut_agent/common/utils.py
walnut_agent/script/__init__.py
walnut_agent/script/agent.py
walnut_agent/script/app_handle.py
walnut_agent/script/case_class.py
walnut_agent/script/flask_client.py
walnut_agent/script/http_handle.py
walnut_agent/script/operation.py
walnut_agent/script/qiniu.py
walnut_agent/script/runner.py
walnut_agent/script/util_handle.py
walnut_agent/script/ws_client.py
walnut_agent/script/ws_server.py
walnut_agent/static/lib/bixin-runner.ipa
walnut_agent/static/lib/wda-bixin.ipa
walnut_agent/unit/__init__.py
walnut_agent/unit/dingtalk.md
walnut_agent/unit/email_templates.html
walnut_agent/unit/report.py
walnut_agent/unit/resultPush.py
walnut_agent/unit/templates.html
walnut_agent/unit/testResult.py
HuTao_agent-1.0.3.dist-info/METADATA
HuTao_agent-1.0.3.dist-info/WHEEL
HuTao_agent-1.0.3.dist-info/entry_points.txt
HuTao_agent-1.0.3.dist-info/top_level.txt
HuTao_agent-1.0.3.dist-info/RECORD
